my_multitool/__init__.py
my_multitool/__main__.py
my_multitool/cli_config.py
my_multitool/cli_config_contexts.py
my_multitool/cli_database.py
my_multitool/cli_users.py
my_multitool/config.py
my_multitool/exceptions.py
my_multitool/globals.py
my_multitool/models.py
my_multitool/py.typed
my_multitool/style.py
ds_my_multitool-1.0.6.dist-info/LICENSE.md
ds_my_multitool-1.0.6.dist-info/METADATA
ds_my_multitool-1.0.6.dist-info/WHEEL
ds_my_multitool-1.0.6.dist-info/entry_points.txt
ds_my_multitool-1.0.6.dist-info/RECORD
